{"frames": {

"fogo1.png":
{
	"frame": {"x":0,"y":0,"w":32,"h":32},
	"rotated": false,
	"trimmed": false,
	"spriteSourceSize": {"x":0,"y":0,"w":32,"h":32},
	"sourceSize": {"w":32,"h":32},
	"pivot": {"x":0.5,"y":0.5}
},
"fogo2.png":
{
	"frame": {"x":32,"y":0,"w":32,"h":32},
	"rotated": false,
	"trimmed": false,
	"spriteSourceSize": {"x":0,"y":0,"w":32,"h":32},
	"sourceSize": {"w":32,"h":32},
	"pivot": {"x":0.5,"y":0.5}
}},
"meta": {
	"app": "http://www.codeandweb.com/texturepacker",
	"version": "1.0",
	"image": "explosion.png",
	"format": "RGBA8888",
	"size": {"w":64,"h":32},
	"scale": "1",
	"smartupdate": "$TexturePacker:SmartUpdate:a2b3beba9abe53f881ef044a1de589d1:22750a0b2a0328cfa7a0391f37877601:900e1fb3093a9a6ecb2b2b49071c44f7$"
}
}
